<?xml version="1.0" encoding="utf-8"?>
<Defs>

    <!-- TOZ-34 Dvustvolka -->
	<RecipeDef ParentName="RangedWeaponRecipeBase">
		<defName>BuildDvustvolka</defName>
		<label>Build TOZ-34 Dvustvolka</label>
		<description>Builds an grandfather gun for hunting and personal defence.\nCaliber: 12 Gauge</description>
		<jobString>Building TOZ-34 Dvustvolka.</jobString>
		<workAmount>6900</workAmount>
		<skillRequirements>
			<Crafting>5</Crafting>
		</skillRequirements>
		<ingredients>
			<li>
				<filter>
					<thingDefs>
						<li>Shotgun_Component</li>
					</thingDefs>
				</filter>
				<count>1</count>
			</li>
			<li>
				<filter>
					<thingDefs>
						<li>Weapon_Parts</li>
					</thingDefs>
				</filter>
				<count>2</count>
			</li>
			<li>
				<filter>
					<thingDefs>
						<li>ComponentIndustrial</li>
					</thingDefs>
				</filter>
				<count>8</count>
			</li>
			<li>
				<filter>
					<categories>
						<li>Metallic</li>
					</categories>
				</filter>
				<count>30</count>
			</li>
			<li>
				<filter>
					<categories>
						<li>Woody</li>
					</categories>
				</filter>
				<count>15</count>
			</li>
			<li>
				<filter>
					<categories>
						<li>Leathers</li>
					</categories>
				</filter>
				<count>15</count>
			</li>
		</ingredients>
		<products>
			<Gun_Dvustvolka>1</Gun_Dvustvolka>
		</products>
		<fixedIngredientFilter>
			<thingDefs>
				<li>Shotgun_Component</li>
				<li>Weapon_Parts</li>
				<li>ComponentIndustrial</li>
			</thingDefs>
			<categories>
				<li>SLDBar</li>
				<li>USLDBar</li>
				<li>Woody</li>
				<li>Leathers</li>
			</categories>
		</fixedIngredientFilter>
		<recipeUsers>
			<li>WeaponCraftingWorkTable</li>
		</recipeUsers>
	</RecipeDef>

    <!-- Saiga12k -->
	<RecipeDef ParentName="RangedWeaponRecipeBase">
		<defName>BuildSaiga12kShotgun</defName>
		<label>Build Saiga12k</label>
		<description>Builds an Saiga12k, an semi-automatic shotgun. Has burst fire, is moderately accurate at just under rifle range and has high damage output.\nCaliber: 12 Gauge</description>
		<jobString>Building Saiga12k.</jobString>
		<workAmount>15000</workAmount>
		<skillRequirements>
			<Crafting>10</Crafting>
		</skillRequirements>
		<ingredients>
			<li>
				<filter>
					<thingDefs>
						<li>Shotgun_Component</li>
					</thingDefs>
				</filter>
				<count>1</count>
			</li>
			<li>
				<filter>
					<thingDefs>
						<li>Weapon_Parts</li>
					</thingDefs>
				</filter>
				<count>10</count>
			</li>
			<li>
				<filter>
					<thingDefs>
						<li>ComponentIndustrial</li>
					</thingDefs>
				</filter>
				<count>12</count>
			</li>
			<li>
				<filter>
					<categories>
						<li>Metallic</li>
					</categories>
				</filter>
				<count>35</count>
			</li>
			<li>
				<filter>
					<categories>
						<li>Woody</li>
					</categories>
				</filter>
				<count>30</count>
			</li>
			<li>
				<filter>
					<categories>
						<li>Leathers</li>
					</categories>
				</filter>
				<count>15</count>
			</li>
		</ingredients>
		<products>
			<Gun_Saiga12k>1</Gun_Saiga12k>
		</products>
		<fixedIngredientFilter>
			<thingDefs>
				<li>Shotgun_Component</li>
				<li>Weapon_Parts</li>
				<li>ComponentIndustrial</li>
			</thingDefs>
			<categories>
				<li>SLDBar</li>
				<li>USLDBar</li>
				<li>Woody</li>
				<li>Leathers</li>
			</categories>
		</fixedIngredientFilter>
		<recipeUsers>
			<li>WeaponCraftingWorkTable</li>
		</recipeUsers>
	</RecipeDef>

    <!-- Saw of Shotgun -->
	<RecipeDef ParentName="RangedWeaponRecipeBase">
		<defName>BuildSawofShotgun</defName>
		<label>Build Saw of Shotgun</label>
		<description>Builds an ancient shotgun for personal defence.\nCaliber: 12 Gauge</description>
		<jobString>Building Saw of Shotgun.</jobString>
		<workAmount>6000</workAmount>
		<skillRequirements>
			<Crafting>4</Crafting>
		</skillRequirements>
		<ingredients>
			<li>
				<filter>
					<thingDefs>
						<li>Shotgun_Component</li>
					</thingDefs>
				</filter>
				<count>1</count>
			</li>
			<li>
				<filter>
					<thingDefs>
						<li>Weapon_Parts</li>
					</thingDefs>
				</filter>
				<count>1</count>
			</li>
			<li>
				<filter>
					<thingDefs>
						<li>ComponentIndustrial</li>
					</thingDefs>
				</filter>
				<count>6</count>
			</li>
			<li>
				<filter>
					<categories>
						<li>Metallic</li>
					</categories>
				</filter>
				<count>20</count>
			</li>
			<li>
				<filter>
					<categories>
						<li>Woody</li>
					</categories>
				</filter>
				<count>10</count>
			</li>
			<li>
				<filter>
					<categories>
						<li>Leathers</li>
					</categories>
				</filter>
				<count>10</count>
			</li>
		</ingredients>
		<products>
			<Gun_SawofShotgun>1</Gun_SawofShotgun>
		</products>
		<fixedIngredientFilter>
			<thingDefs>
				<li>Shotgun_Component</li>
				<li>Weapon_Parts</li>
				<li>ComponentIndustrial</li>
			</thingDefs>
			<categories>
				<li>SLDBar</li>
				<li>USLDBar</li>
				<li>Woody</li>
				<li>Leathers</li>
			</categories>
		</fixedIngredientFilter>
		<recipeUsers>
			<li>WeaponCraftingWorkTable</li>
		</recipeUsers>
	</RecipeDef>

    <!-- Spas-12 -->
	<RecipeDef ParentName="RangedWeaponRecipeBase">
		<defName>BuildSpas12HMC</defName>
		<label>Build Sps-12\20 Shotgun</label>
		<description>Builds an Special forces auto shotgun.\nCaliber: 12 Gauge</description>
		<jobString>Building Spas-12.</jobString>
		<workAmount>20400</workAmount>
		<skillRequirements>
			<Crafting>14</Crafting>
		</skillRequirements>
		<ingredients>
			<li>
				<filter>
					<thingDefs>
						<li>Shotgun_Component</li>
					</thingDefs>
				</filter>
				<count>1</count>
			</li>
			<li>
				<filter>
					<thingDefs>
						<li>Weapon_Parts</li>
					</thingDefs>
				</filter>
				<count>12</count>
			</li>
			<li>
				<filter>
					<thingDefs>
						<li>ComponentIndustrial</li>
					</thingDefs>
				</filter>
				<count>12</count>
			</li>
			<li>
				<filter>
					<categories>
						<li>Metallic</li>
					</categories>
				</filter>
				<count>50</count>
			</li>
			<li>
				<filter>
					<thingDefs>
						<li>Plastic</li>
					</thingDefs>
				</filter>
				<count>50</count>
			</li>
			<li>
				<filter>
					<categories>
						<li>Leathers</li>
					</categories>
				</filter>
				<count>18</count>
			</li>
		</ingredients>
		<products>
			<Spas12_HMC>1</Spas12_HMC>
		</products>
		<fixedIngredientFilter>
			<thingDefs>
				<li>Shotgun_Component</li>
				<li>Weapon_Parts</li>
				<li>ComponentIndustrial</li>
				<li>Plastic</li>
			</thingDefs>
			<categories>
				<li>SLDBar</li>
				<li>USLDBar</li>
				<li>Leathers</li>
			</categories>
		</fixedIngredientFilter>
		<recipeUsers>
			<li>AdvWeaponCraftingWorkTable</li>
		</recipeUsers>
	</RecipeDef>

    <!-- TOZ-2077 High-tech dvustvolka -->
	<RecipeDef ParentName="RangedWeaponRecipeBase">
		<defName>Build_HMC_TozHighTech</defName>
		<label>Build high-tech Dvustvolka</label>
		<description>Builds an grandfather high-tech gun for hunting and personal defence.\nCaliber: 15x65mm Diffusing Charged</description>
		<jobString>Building high-tech Dvustvolka.</jobString>
		<workAmount>28200</workAmount>
		<skillRequirements>
			<Crafting>14</Crafting>
		</skillRequirements>
		<ingredients>
			<li>
				<filter>
					<thingDefs>
						<li>Plasma_Component</li>
					</thingDefs>
				</filter>
				<count>1</count>
			</li>
			<li>
				<filter>
					<thingDefs>
						<li>Shotgun_Component</li>
					</thingDefs>
				</filter>
				<count>2</count>
			</li>
			<li>
				<filter>
					<thingDefs>
						<li>Weapon_Parts</li>
					</thingDefs>
				</filter>
				<count>5</count>
			</li>
			<li>
				<filter>
					<thingDefs>
						<li>ComponentSpacer</li>
					</thingDefs>
				</filter>
				<count>8</count>
			</li>
			<li>
				<filter>
					<categories>
						<li>USLDBar</li>
					</categories>
				</filter>
				<count>30</count>
			</li>
			<li>
				<filter>
					<thingDefs>
						<li>Plastic</li>
					</thingDefs>
				</filter>
				<count>20</count>
			</li>
		</ingredients>
		<products>
			<HMC_TozHighTech>1</HMC_TozHighTech>
		</products>
		<fixedIngredientFilter>
			<thingDefs>
				<li>Plasma_Component</li>
				<li>Shotgun_Component</li>
				<li>Weapon_Parts</li>
				<li>ComponentSpacer</li>
				<li>Plastic</li>
			</thingDefs>
			<categories>
				<li>USLDBar</li>
			</categories>
		</fixedIngredientFilter>
		<recipeUsers>
			<li>MechWeaponCraftingWorkTable</li>
		</recipeUsers>
	</RecipeDef>

</Defs>