<?xml version="1.0" encoding="utf-8"?>
<LanguageData>

  <SuperCCleaner.degreeDatas.0.label>уборщик</SuperCCleaner.degreeDatas.0.label>
  <SuperCCleaner.degreeDatas.0.description>{PAWN_nameDef} объект любви и восхищения в каждой колонии... восхищайся или будешь наказан!</SuperCCleaner.degreeDatas.0.description>
  
  <Huntman.degreeDatas.0.label>лесной охотник</Huntman.degreeDatas.0.label>
  <Huntman.degreeDatas.0.description>{PAWN_nameDef} посвятил свою жизнь охотничьему ремеслу и без труда может свалить с ног даже мегабарсука!</Huntman.degreeDatas.0.description>
  
  <Radiomechanician.degreeDatas.0.label>радиомеханик</Radiomechanician.degreeDatas.0.label>
  <Radiomechanician.degreeDatas.0.description>{PAWN_nameDef} - радиомеханик и без труда может собрать вафельницу из старых процессоров! Главное не давайте готовить вафли самостоятельно!</Radiomechanician.degreeDatas.0.description>
  
  <GreaterBlacksmith.degreeDatas.0.label>кузнец</GreaterBlacksmith.degreeDatas.0.label>
  <GreaterBlacksmith.degreeDatas.0.description>{PAWN_nameDef} - кузнец. Будучи кузнецом, {PAWN_pronoun} мечтает создавать легендарное оружие, но из-за ненадобности в оном большая часть работы - переплавка всякого хлама, который приносят с собой рейды.</GreaterBlacksmith.degreeDatas.0.description>
  
  <GreenThumbTwo.degreeDatas.0.label>хороший садовник</GreenThumbTwo.degreeDatas.0.label>
  <GreenThumbTwo.degreeDatas.0.description>[PAWN_nameDef] хороший садовник. [PAWN_pronoun] единственное желание это озеленить весь мир!</GreenThumbTwo.degreeDatas.0.description>
  
  <Efficaciousness.degreeDatas.0.label>эффективность</Efficaciousness.degreeDatas.0.label>
  <Efficaciousness.degreeDatas.0.description>{PAWN_nameDef} - само совершенство.</Efficaciousness.degreeDatas.0.description>
  
  <StrongBack.degreeDatas.0.label>тяжеловоз</StrongBack.degreeDatas.0.label>
  <StrongBack.degreeDatas.0.description>{PAWN_nameDef} подобно одноименной породе лошадей переносит значительно больше, чем сородичи. Иногда кажется, что {PAWN_pronoun} может унести горы на своих плечах.</StrongBack.degreeDatas.0.description>
   
  <BlueNivaWorker.degreeDatas.0.label>труженик голубой нивы</BlueNivaWorker.degreeDatas.0.label>
  <BlueNivaWorker.degreeDatas.0.description>Бросить наживку и набраться терпения. Привыкнув к подобной жизни, {PAWN_nameDef} не только обладает отличными навыками рыболова, но и может сохранять абсолютное спокойствие часами.</BlueNivaWorker.degreeDatas.0.description>
   
  <SleightOfHand.degreeDatas.0.label>ловкость рук</SleightOfHand.degreeDatas.0.label>
  <SleightOfHand.degreeDatas.0.description>Любимым детским занятием {PAWN_nameDef} было посещение пригородного цирка, а любимым представлением - жонглирование обогощённым ураном голыми руками! Урана, конечно, у {PAWN_nameDef} никогда не было, но это не помешало {PAWN_nameDef} развивать свои навыки в этом направлении!</SleightOfHand.degreeDatas.0.description>
   
  <AtelierTailor.degreeDatas.0.label>швея ателье</AtelierTailor.degreeDatas.0.label>
  <AtelierTailor.degreeDatas.0.description>Родившись в семье портных и швей и усвоив все премудрости данного ремесла, {PAWN_nameDef} с удовольствием разрешит ваши проблемы с разборкой труповой одежды!</AtelierTailor.degreeDatas.0.description>
   
  <Morbid.degreeDatas.0.label>мрачный</Morbid.degreeDatas.0.label>
  <Morbid.degreeDatas.0.description>{PAWN_nameDef} питает страсть к мёртвым телам. {PAWN_pronoun} не имеет ничего против брошенных в округе тел, иногда даже выкапывая их, чтобы насладиться всеми их прелестями (особенно одеждой).</Morbid.degreeDatas.0.description>
   
  <Collector.degreeDatas.0.label>собиратель</Collector.degreeDatas.0.label>
  <Collector.degreeDatas.0.description>{PAWN_nameDef} любитель копаться в мусоре и сорняках в поисках чего-нибудь полезного или ценного.</Collector.degreeDatas.0.description>

  <Mastergourmet.degreeDatas.0.label>мастер-кулинар</Mastergourmet.degreeDatas.0.label>
  <Mastergourmet.degreeDatas.0.description>{PAWN_nameDef} имеет столь сильную страсть к приготовлению пищи, что приготовленная пища никогда не захочет выйти наружу. Постоянные пробы подтверждают это!</Mastergourmet.degreeDatas.0.description>

  <CloseCombatSpecialist.degreeDatas.0.label>мастер ближнего боя</CloseCombatSpecialist.degreeDatas.0.label>
  <CloseCombatSpecialist.degreeDatas.0.description>{PAWN_nameDef} отлично умеет обращаться с огнестрельным оружием, но не любит сидеть в стороне во время заварушки!</CloseCombatSpecialist.degreeDatas.0.description>

  <CatInHead.degreeDatas.0.label>мяуржимый</CatInHead.degreeDatas.0.label>
  <CatInHead.degreeDatas.0.description>{PAWN_nameDef} родился слабым и болезненным ребёнком. Попытки лечения от тяжёлого недуга привели жителей села к проведению тайного обряда: жертвоприношения и вселения души животного. В качестве жертвы выбрали мимокрокодящего бедного бродячего котеича. Хотя {PAWN_nameDef} и быстро пошел на поправку, став ловче и здоровее при этом, такое соседство периодически сводит {PAWN_possessive} с ума.</CatInHead.degreeDatas.0.description>

  <Snipermasterrk.degreeDatas.0.label>scharfschützenmeister</Snipermasterrk.degreeDatas.0.label>
  <Snipermasterrk.degreeDatas.0.description>Долгое ожидание принесло плоды.
Цель на горизонте. Шарф на голове.
Бум! Верный выстрел! Но.
Неуязвимость...</Snipermasterrk.degreeDatas.0.description>

  <HMC_Architect.degreeDatas.0.label>архитектор</HMC_Architect.degreeDatas.0.label>
  <HMC_Architect.degreeDatas.0.description>Несмотря на гордое звание создателя прекрасного и великого, пешка {PAWN_nameDef} провела большую часть своей жизни над созданием проектов идеальной коробочки. Не стоит ждать чего-либо красивого от н[PAWN_possessive].</HMC_Architect.degreeDatas.0.description>

  <HMC_IncombustibleEmber.degreeDatas.0.label>негорящий уголек</HMC_IncombustibleEmber.degreeDatas.0.label>
  <HMC_IncombustibleEmber.degreeDatas.0.description>Постоянные срывы, сильные бомбежки и сотни сожженных стульев – кожа {PAWN_nameDef} претерпела столь сильные изменения, что никогда не загорится более.</HMC_IncombustibleEmber.degreeDatas.0.description>

  <HMC_Glasspawnon.degreeDatas.0.label>стеклопешка</HMC_Glasspawnon.degreeDatas.0.label>
  <HMC_Glasspawnon.degreeDatas.0.description>Пожалуйста, берегите {PAWN_possessive}...</HMC_Glasspawnon.degreeDatas.0.description>

  <HMC_SeekerOfDeepSense.degreeDatas.0.label>искатель глубинного смысла</HMC_SeekerOfDeepSense.degreeDatas.0.label>
  <HMC_SeekerOfDeepSense.degreeDatas.0.description>Во вред себе, своим навыкам и самое главное неизвестно зачем {PAWN_nameDef} долгое время занимается изучением глубинного смысла бытия... в буквальном смысле зарываясь под землю, игнорируя опасность инсектоидов. Заводя свой бур, {PAWN_nameDef} впадает в берсерко-подобное состояние «ви-ви-ви-ви-ви-ви-ви». В этом состоянии {PAWN_nameDef} не может двигаться, {PAWN_pronoun} не чувствует ни страха, ни жалости, и только «тыр-тыр-тыр» способен остановить {PAWN_possessive}.</HMC_SeekerOfDeepSense.degreeDatas.0.description>

  <HMC_WellEndowed.degreeDatas.0.label>идеальное тело</HMC_WellEndowed.degreeDatas.0.label>
  <HMC_WellEndowed.degreeDatas.0.description>Природа наградила {PAWN_nameDef} идеальным телом. Гибкие бёдра и упругие ягодицы не только предмет гордости и объект вожделения у особ противоположного пола, но и великолепный инструмент, упрощающий жизнь и тяжёлый труд.</HMC_WellEndowed.degreeDatas.0.description>

  <HMC_NonWellEndowed.degreeDatas.0.label>широкая кость</HMC_NonWellEndowed.degreeDatas.0.label>
  <HMC_NonWellEndowed.degreeDatas.0.description>Природа наградила {PAWN_nameDef} не совсем идеальным телом. Тучные бёдра и ягодицы не вызывают вожделения у особ противоположного пола, но зато служат неплохим естественным барьером и помогут спасти от голодной смерти ваших товарищей!</HMC_NonWellEndowed.degreeDatas.0.description>

  <HMC_TouchOfNature.degreeDatas.0.label>близость к природе</HMC_TouchOfNature.degreeDatas.0.label>
  <HMC_TouchOfNature.degreeDatas.0.description>{PAWN_nameDef} имеет сильную связь с природой. Радости светской жизний чужды {PAWN_possessive}.\n\nНедоступные виды медитации: возвышенность и искусство.</HMC_TouchOfNature.degreeDatas.0.description>

  <HMC_IronFist.degreeDatas.0.label>ежовые рукавицы</HMC_IronFist.degreeDatas.0.label>
  <HMC_IronFist.degreeDatas.0.description>{PAWN_nameDef} считает, что лучшая наука та, что крушит черепа в обход волшебных щитов!</HMC_IronFist.degreeDatas.0.description>

</LanguageData>