<?xml version="1.0" encoding="utf-8"?>
<LanguageData>

  <LandShark.label>сухопутная акула</LandShark.label>
  <LandShark.description>...коробочка...вкусняшка...</LandShark.description>
  <Corpse_LandShark.label>труп сухопутной акулы</Corpse_LandShark.label>
  <Corpse_LandShark.description>Труп сухопутной акулы.</Corpse_LandShark.description>

  <Jackalope.label>рогатый заяц</Jackalope.label>
  <Jackalope.description>Странный генетически модифицированный вид кролика с острыми рогами, растущими из черепа. Очень опасен в больших количествах.</Jackalope.description>
  <Corpse_Jackalope.label>труп рогатого зайца</Corpse_Jackalope.label>
  <Corpse_Jackalope.description>Труп рогатого зайца.</Corpse_Jackalope.description>

  <SnowJackalope.label>снежный рогатый заяц</SnowJackalope.label>
  <SnowJackalope.description>Странный генетически модифицированный вид кролика с острыми рогами, растущими из черепа. Очень опасен в больших количествах.</SnowJackalope.description>
  <Corpse_SnowJackalope.label>труп снежного рогатого зайца</Corpse_SnowJackalope.label>
  <Corpse_SnowJackalope.description>Труп снежного рогатого зайца.</Corpse_SnowJackalope.description>

  <Hiveguardsman.label>гвардеец улья</Hiveguardsman.label>
  <Hiveguardsman.description>Гигантский генетически модифицированный инсектоид размером с носорога, созданный для тяжёлый работы и боя. Его защищает толстая хитиновая броня, а длинные потрошащие клинки смертельно опасны в ближнем бою. На открытой местности весьма медлителен.</Hiveguardsman.description>
  <Corpse_Hiveguardsman.label>труп гвардейца улья</Corpse_Hiveguardsman.label>
  <Corpse_Hiveguardsman.description>Труп гвардейца улья.</Corpse_Hiveguardsman.description>

  <HMC_beaver.label>бобр</HMC_beaver.label>
  <HMC_beaver.description>бобёр обыкновенный.</HMC_beaver.description>
  <Corpse_HMC_beaver.label>тушка бобра</Corpse_HMC_beaver.label>
  <Corpse_HMC_beaver.description>Мёртвый бобр.</Corpse_HMC_beaver.description>

  <HMC_Penguin.label>пингвин</HMC_Penguin.label>
  <HMC_Penguin.description>Водная нелетающая птица, обитающая преимущественно в арктических регионах. Пингвины, которых часто можно увидеть большими стаями, агрессивны, когда их загоняют в угол, и могут быстро напасть на любого некомпетентного охотника, чтобы приблизиться к нему.</HMC_Penguin.description>
  <Corpse_HMC_Penguin.label>тушка пингвина</Corpse_HMC_Penguin.label>
  <Corpse_HMC_Penguin.description>Мёртвый пингвин.</Corpse_HMC_Penguin.description>

  <HMC_Lion.label>лев</HMC_Lion.label>
  <HMC_Lion.description>Царь животного мира, лев — мускулистая кошка с развитой грудной клеткой, короткой головой и выступающей гривой. Будучи самыми крупными представителями кошачьих, львы являются отличными боевыми животными, несмотря на свою дикость.</HMC_Lion.description>
  <Corpse_HMC_Lion.label>тушка льва</Corpse_HMC_Lion.label>
  <Corpse_HMC_Lion.description>Мёртвый лев.</Corpse_HMC_Lion.description>

</LanguageData>